{
    "@context": "https://doi.org/10.5063/schema/codemeta-2.0",
    "@type": "SoftwareSourceCode",
    "license": "https://spdx.org/licenses/AGPL-3.0-or-later",
    "codeRepository": "git+https://github.com/PenRed/PenRed.git",
    "dateCreated": "2019-10-01",
    "datePublished": "2020-03-02",
    "dateModified": "2020-03-02",
    "downloadUrl": "https://github.com/PenRed/PenRed/archive/v1.0.tar.gz",
    "issueTracker": "https://github.com/PenRed/PenRed/issues",
    "name": "PenRed",
    "version": "1.0.0",
    "description": "PenRed is a fully parallel, modular and customizable framework for Monte-Carlo simulations of the passage of radiation through matter. ",
    "applicationCategory": "Physics, Medical Physics",
    "developmentStatus": "active",
    "referencePublication": "arXiv:2003.00796",
    "keywords": [
        "Radiation transport",
        "Monte Carlo simulation",
        "Electron-photonshowers",
        "Parallel computing",
        "MPI",
        "Medical physics"
    ],
    "programmingLanguage": [
        "C++"
    ],
    "operatingSystem": [
        "Linux"
    ],
    "author": [
        {
            "@type": "Person",
            "@id": "https://orcid.org/0000-0003-1646-6094",
            "givenName": "Vicent",
            "familyName": "Giménez Alventosa",
            "email": "vicent.gimenez.alventosa@gmail.com",
            "affiliation": {
                "@type": "Organization",
                "name": "Instituto de Instrumentación para Imagen Molecular (I3M) Centro mixto CSIC - Universitat Politècnica de València"
            }
        },
        {
            "@type": "Person",
            "@id": "https://orcid.org/0000-0003-3855-2567",
            "givenName": "Vicente",
            "familyName": "Giménez Gómez",
            "email": "vicente.gimenez@uv.es",
            "affiliation": {
                "@type": "Organization",
                "name": "Departament de Física Teòrica and IFIC Universitat de València-CSIC"
            }
        },
        {
            "@type": "Person",
            "@id": "http://orcid.org/0000-0001-8258-3972",
            "givenName": "Sandra",
            "familyName": "Oliver Gil",
            "email": "sanolgi@upvnet.upv.es",
            "affiliation": {
                "@type": "Organization",
                "name": "Instituto de Seguridad Industrial, Radiofísica y Medioambiental (ISIRYM) Universitat Politècnica de València"
            }
        }
    ]
}
